{
    "source": "https://ianring.com/musictheory/scales/traditions/dozenal",
    "1": "0ian",
    "3": "1ian",
    "5": "2ian",
    "7": "ABOian",
    "9": "3ian",
    "11": "ANKian",
    "13": "DIJian",
    "15": "TEJian",
    "17": "4ian",
    "19": "ACUian",
    "21": "ACLian",
    "23": "APHian",
    "25": "ACKian",
    "27": "ADOian",
    "29": "ADUian",
    "31": "AFFian",
    "33": "5ian",
    "35": "ABBian",
    "37": "AFOian",
    "39": "AFUian",
    "41": "ACHian",
    "43": "ALFian",
    "45": "APRian",
    "47": "AGOian",
    "49": "AGUian",
    "51": "ARFian",
    "53": "ABSian",
    "55": "ASPian",
    "57": "AHOian",
    "59": "AHUian",
    "61": "AJUian",
    "63": "ABLian",
    "65": "6ian",
    "67": "ABRian",
    "69": "DEZian",
    "71": "ALOian",
    "73": "DIMian",
    "75": "ILOian",
    "77": "ALVian",
    "79": "APPian",
    "81": "DISian",
    "83": "AMUian",
    "85": "SEGian",
    "87": "ASRian",
    "89": "AGGian",
    "91": "ANOian",
    "93": "ANUian",
    "95": "ARKian",
    "97": "ATHian",
    "99": "IPRian",
    "101": "APOian",
    "103": "APUian",
    "105": "EDWian",
    "107": "ANSian",
    "109": "AMSian",
    "111": "AROian",
    "113": "ARUian",
    "115": "ASHian",
    "117": "ANBian",
    "119": "SMOian",
    "121": "ASOian",
    "123": "ASUian",
    "125": "ATWian",
    "127": "TIZian",
    "129": "7ian",
    "131": "ATOian",
    "133": "REPian",
    "135": "ATTian",
    "137": "MINian",
    "139": "AYOian",
    "141": "BABian",
    "143": "BACian",
    "145": "MAJian",
    "147": "BAFian",
    "149": "BEJian",
    "151": "BAHian",
    "153": "BAJian",
    "155": "BAKian",
    "157": "BALian",
    "159": "BAMian",
    "161": "SUSian",
    "163": "BAPian",
    "165": "BAQian",
    "167": "BARian",
    "169": "BASian",
    "171": "PRUian",
    "173": "BAVian",
    "175": "BEWian",
    "177": "BEXian",
    "179": "BEYian",
    "181": "BEZian",
    "183": "BEBian",
    "185": "BECian",
    "187": "BEDian",
    "189": "BEFian",
    "191": "BEGian",
    "193": "BEHian",
    "195": "BAGian",
    "197": "BEKian",
    "199": "BELian",
    "201": "BEMian",
    "203": "ICHian",
    "205": "BEPian",
    "207": "BEQian",
    "209": "BIRian",
    "211": "BISian",
    "213": "BITian",
    "215": "BIVian",
    "217": "BIWian",
    "219": "BIXian",
    "221": "BIYian",
    "223": "BIZian",
    "225": "BIBian",
    "227": "BICian",
    "229": "BIDian",
    "231": "BIFian",
    "233": "BIGian",
    "235": "BIHian",
    "237": "BIJian",
    "239": "BIKian",
    "241": "BILian",
    "243": "BOMian",
    "245": "BONian",
    "247": "BOPian",
    "249": "BOQian",
    "251": "BORian",
    "253": "BOSian",
    "255": "BOTian",
    "257": "8ian",
    "259": "GIJian",
    "261": "BOZian",
    "263": "UDWian",
    "265": "BOXian",
    "267": "BOBian",
    "269": "BOCian",
    "271": "BODian",
    "273": "AUGian",
    "275": "HUZian",
    "277": "BUHian",
    "279": "BUJian",
    "281": "BUKian",
    "283": "BULian",
    "285": "BUMian",
    "287": "BUNian",
    "289": "VALian",
    "291": "MUZian",
    "293": "BURian",
    "295": "BUSian",
    "297": "ARTian",
    "299": "BUVian",
    "301": "BUWian",
    "303": "BUXian",
    "305": "BUYian",
    "307": "BUZian",
    "309": "BUBian",
    "311": "CABian",
    "313": "CACian",
    "315": "CADian",
    "317": "CAFian",
    "319": "CAGian",
    "321": "CAHian",
    "323": "CAJian",
    "325": "CARian",
    "327": "CALian",
    "329": "CAMian",
    "331": "CANian",
    "333": "CAPian",
    "335": "CAQian",
    "337": "CAKian",
    "339": "CASian",
    "341": "FROian",
    "343": "CAVian",
    "345": "CEWian",
    "347": "CEXian",
    "349": "CEYian",
    "351": "CEZian",
    "353": "CEBian",
    "355": "CECian",
    "357": "CEDian",
    "359": "CEFian",
    "361": "CEGian",
    "363": "CEHian",
    "365": "CEJian",
    "367": "CEKian",
    "369": "CELian",
    "371": "CEMian",
    "373": "INKian",
    "375": "CEPian",
    "377": "CEQian",
    "379": "CIRian",
    "381": "CISian",
    "383": "CITian",
    "385": "CIVian",
    "387": "CIWian",
    "389": "CIXian",
    "391": "CIYian",
    "393": "CIZian",
    "395": "CIBian",
    "397": "CICian",
    "399": "CIDian",
    "401": "CIFian",
    "403": "CIGian",
    "405": "CIHian",
    "407": "CIJian",
    "409": "CIKian",
    "411": "CILian",
    "413": "COMian",
    "415": "CONian",
    "417": "COPian",
    "419": "COQian",
    "421": "CORian",
    "423": "COSian",
    "425": "COTian",
    "427": "COVian",
    "429": "SKOian",
    "431": "COXian",
    "433": "COYian",
    "435": "COZian",
    "437": "COBian",
    "439": "COCian",
    "441": "CODian",
    "443": "COFian",
    "445": "COGian",
    "447": "CUHian",
    "449": "CUJian",
    "451": "CUKian",
    "453": "CULian",
    "455": "STOian",
    "457": "CUNian",
    "459": "CUPian",
    "461": "CUQian",
    "463": "CURian",
    "465": "CUSian",
    "467": "CUTian",
    "469": "CUVian",
    "471": "CUWian",
    "473": "CUXian",
    "475": "CUYian",
    "477": "CUZian",
    "479": "UPRian",
    "481": "DABian",
    "483": "DACian",
    "485": "DADian",
    "487": "DAFian",
    "489": "DAGian",
    "491": "DAHian",
    "493": "DAJian",
    "495": "DAKian",
    "497": "DALian",
    "499": "DAMian",
    "501": "DANian",
    "503": "DAPian",
    "505": "DAQian",
    "507": "DARian",
    "509": "DASian",
    "511": "DATian",
    "513": "9ian",
    "515": "DEPian",
    "517": "ALUian",
    "519": "DEYian",
    "521": "ASTian",
    "523": "DEBian",
    "525": "IDWian",
    "527": "DEDian",
    "529": "REMian",
    "531": "DEGian",
    "533": "DEHian",
    "535": "DEJian",
    "537": "ATUian",
    "539": "DELian",
    "541": "DEMian",
    "543": "DENian",
    "545": "DEWian",
    "547": "KOPian",
    "549": "DIRian",
    "551": "ULVian",
    "553": "DITian",
    "555": "DIVian",
    "557": "DIWian",
    "559": "DIXian",
    "561": "DIYian",
    "563": "DIZian",
    "565": "DIBian",
    "567": "DICian",
    "569": "DIDian",
    "571": "DIFian",
    "573": "DIGian",
    "575": "DIHian",
    "577": "ILLian",
    "579": "GIYian",
    "581": "DILian",
    "583": "DONian",
    "585": "FULian",
    "587": "DOPian",
    "589": "DOQian",
    "591": "HEYian",
    "593": "DOSian",
    "595": "DOTian",
    "597": "DOVian",
    "599": "OGRian",
    "601": "DOXian",
    "603": "DOYian",
    "605": "HATian",
    "607": "DOBian",
    "609": "DOCian",
    "611": "DODian",
    "613": "DOFian",
    "615": "SKUian",
    "617": "DUHian",
    "619": "DUJian",
    "621": "DUKian",
    "623": "DULian",
    "625": "DUMian",
    "627": "DUNian",
    "629": "DUPian",
    "631": "DUQian",
    "633": "DURian",
    "635": "DUSian",
    "637": "DUTian",
    "639": "DUVian",
    "641": "DUWian",
    "643": "DUXian",
    "645": "DUYian",
    "647": "DUZian",
    "649": "DUBian",
    "651": "EBLian",
    "653": "ESKian",
    "655": "EPRian",
    "657": "EBOian",
    "659": "EBUian",
    "661": "ULTian",
    "663": "EBRian",
    "665": "ENSian",
    "667": "ECOian",
    "669": "ECUian",
    "671": "SANian",
    "673": "ESTian",
    "675": "EMSian",
    "677": "HENian",
    "679": "EDUian",
    "681": "EPHian",
    "683": "ELFian",
    "685": "ERTian",
    "687": "EFOian",
    "689": "EFUian",
    "691": "ETTian",
    "693": "ESHian",
    "695": "ERFian",
    "697": "EGOian",
    "699": "EGUian",
    "701": "ETHian",
    "703": "EFFian",
    "705": "EDRian",
    "707": "EHOian",
    "709": "EHUian",
    "711": "EJUian",
    "713": "ESRian",
    "715": "ECHian",
    "717": "ENTian",
    "719": "ECKian",
    "721": "ELOian",
    "723": "ELUian",
    "725": "EBBian",
    "727": "ELTian",
    "729": "OFRian",
    "731": "EMOian",
    "733": "EMUian",
    "735": "ECLian",
    "737": "TRUian",
    "739": "EPLian",
    "741": "ENOian",
    "743": "ENUian",
    "745": "EPPian",
    "747": "ERGian",
    "749": "ETLian",
    "751": "EPOian",
    "753": "EPUian",
    "755": "ESPian",
    "757": "ETWian",
    "759": "ENKian",
    "761": "EROian",
    "763": "ERUian",
    "765": "ERKian",
    "767": "ELVian",
    "769": "ENBian",
    "771": "ESOian",
    "773": "ESUian",
    "775": "ERMian",
    "777": "EMPian",
    "779": "ETRian",
    "781": "ETOian",
    "783": "ETUian",
    "785": "NEPian",
    "787": "ERRian",
    "789": "EYOian",
    "791": "FABian",
    "793": "FACian",
    "795": "FADian",
    "797": "FAFian",
    "799": "USTian",
    "801": "FAHian",
    "803": "FAJian",
    "805": "FAKian",
    "807": "FALian",
    "809": "FAMian",
    "811": "FANian",
    "813": "FAPian",
    "815": "FAQian",
    "817": "FARian",
    "819": "FASian",
    "821": "FATian",
    "823": "FAVian",
    "825": "FEWian",
    "827": "FEXian",
    "829": "FEYian",
    "831": "FEZian",
    "833": "FEBian",
    "835": "FECian",
    "837": "FEDian",
    "839": "FEFian",
    "841": "FEGian",
    "843": "FEHian",
    "845": "FEJian",
    "847": "FEKian",
    "849": "FELian",
    "851": "FEMian",
    "853": "FENian",
    "855": "FEPian",
    "857": "FEQian",
    "859": "FIRian",
    "861": "FISian",
    "863": "FITian",
    "865": "JAHian",
    "867": "FIWian",
    "869": "FIXian",
    "871": "FIYian",
    "873": "FIZian",
    "875": "FIBian",
    "877": "FICian",
    "879": "FIDian",
    "881": "DROian",
    "883": "UDRian",
    "885": "FIHian",
    "887": "EBSian",
    "889": "FIKian",
    "891": "FILian",
    "893": "FOMian",
    "895": "FONian",
    "897": "FOPian",
    "899": "FOQian",
    "901": "BOFian",
    "903": "FOSian",
    "905": "FOTian",
    "907": "FOVian",
    "909": "FOWian",
    "911": "NEKian",
    "913": "FOYian",
    "915": "FOZian",
    "917": "FOBian",
    "919": "FOCian",
    "921": "FODian",
    "923": "FOFian",
    "925": "FOGian",
    "927": "FUHian",
    "929": "FUJian",
    "931": "FUKian",
    "933": "AFRian",
    "935": "FUMian",
    "937": "SPUian",
    "939": "FUPian",
    "941": "FUQian",
    "943": "FURian",
    "945": "FUSian",
    "947": "FUTian",
    "949": "FUVian",
    "951": "FUWian",
    "953": "FUXian",
    "955": "FUYian",
    "957": "FUZian",
    "959": "FUBian",
    "961": "GABian",
    "963": "GACian",
    "965": "GADian",
    "967": "GAFian",
    "969": "GAGian",
    "971": "GAHian",
    "973": "GAJian",
    "975": "GAKian",
    "977": "GALian",
    "979": "GAMian",
    "981": "GANian",
    "983": "GAPian",
    "985": "GAQian",
    "987": "GARian",
    "989": "GASian",
    "991": "GATian",
    "993": "GAVian",
    "995": "GEWian",
    "997": "GEXian",
    "999": "GEYian",
    "1001": "GEZian",
    "1003": "GEBian",
    "1005": "GECian",
    "1007": "GEDian",
    "1009": "GEFian",
    "1011": "GEGian",
    "1013": "GEHian",
    "1015": "GEJian",
    "1017": "GEKian",
    "1019": "GELian",
    "1021": "GEMian",
    "1023": "GENian",
    "1025": "Tian",
    "1027": "GEQian",
    "1029": "AMPian",
    "1031": "GISian",
    "1033": "ALLian",
    "1035": "GIVian",
    "1037": "GIWian",
    "1039": "GIXian",
    "1041": "HITian",
    "1043": "GIZian",
    "1045": "GIBian",
    "1047": "GICian",
    "1049": "GIDian",
    "1051": "GIFian",
    "1053": "GIGian",
    "1055": "GIHian",
    "1057": "BOWian",
    "1059": "GIKian",
    "1061": "GILian",
    "1063": "GOMian",
    "1065": "GONian",
    "1067": "GOPian",
    "1069": "GOQian",
    "1071": "GORian",
    "1073": "GOSian",
    "1075": "GOTian",
    "1077": "GOVian",
    "1079": "GOWian",
    "1081": "GOXian",
    "1083": "GOYian",
    "1085": "GOZian",
    "1087": "GOBian",
    "1089": "GOCian",
    "1091": "PEDian",
    "1093": "GOFian",
    "1095": "GOGian",
    "1097": "HAFian",
    "1099": "GUJian",
    "1101": "AMOian",
    "1103": "GULian",
    "1105": "OPHian",
    "1107": "GUNian",
    "1109": "GUPian",
    "1111": "GUQian",
    "1113": "GURian",
    "1115": "GUSian",
    "1117": "GUTian",
    "1119": "GUVian",
    "1121": "GUWian",
    "1123": "GUXian",
    "1125": "GUYian",
    "1127": "GUZian",
    "1129": "GUBian",
    "1131": "HABian",
    "1133": "HACian",
    "1135": "HADian",
    "1137": "BRUian",
    "1139": "HAGian",
    "1141": "HAHian",
    "1143": "HAJian",
    "1145": "HAKian",
    "1147": "HALian",
    "1149": "HAMian",
    "1151": "HANian",
    "1153": "CHOian",
    "1155": "ADWian",
    "1157": "ALKian",
    "1159": "HASian",
    "1161": "RADian",
    "1163": "HAVian",
    "1165": "HEWian",
    "1167": "OBLian",
    "1169": "DOMian",
    "1171": "HEZian",
    "1173": "HEBian",
    "1175": "HECian",
    "1177": "HEDian",
    "1179": "HEFian",
    "1181": "HEGian",
    "1183": "HEHian",
    "1185": "HEJian",
    "1187": "TROian",
    "1189": "HELian",
    "1191": "HEMian",
    "1193": "WARian",
    "1195": "OPSian",
    "1197": "STUian",
    "1199": "HIRian",
    "1201": "HISian",
    "1203": "SPOian",
    "1205": "HIVian",
    "1207": "HIWian",
    "1209": "HIXian",
    "1211": "HIYian",
    "1213": "HIZian",
    "1215": "HIBian",
    "1217": "HICian",
    "1219": "HIDian",
    "1221": "HIFian",
    "1223": "HIGian",
    "1225": "HIHian",
    "1227": "HIJian",
    "1229": "HIKian",
    "1231": "HILian",
    "1233": "HOMian",
    "1235": "HONian",
    "1237": "HOPian",
    "1239": "HOQian",
    "1241": "GUHian",
    "1243": "HOSian",
    "1245": "BUPian",
    "1247": "HOVian",
    "1249": "HOWian",
    "1251": "HOXian",
    "1253": "HOYian",
    "1255": "HOZian",
    "1257": "HOBian",
    "1259": "HOCian",
    "1261": "HODian",
    "1263": "HOFian",
    "1265": "HOGian",
    "1267": "HUHian",
    "1269": "HUJian",
    "1271": "HUKian",
    "1273": "HULian",
    "1275": "HUMian",
    "1277": "HUNian",
    "1279": "HUPian",
    "1281": "HUQian",
    "1283": "HURian",
    "1285": "HUSian",
    "1287": "HUTian",
    "1289": "HUVian",
    "1291": "HUWian",
    "1293": "HUXian",
    "1295": "HUYian",
    "1297": "BOGian",
    "1299": "HUBian",
    "1301": "ITWian",
    "1303": "ILKian",
    "1305": "IPHian",
    "1307": "IBOian",
    "1309": "IBUian",
    "1311": "ITHian",
    "1313": "IPLian",
    "1315": "IBSian",
    "1317": "ICOian",
    "1319": "ICUian",
    "1321": "BENian",
    "1323": "IRMian",
    "1325": "IBRian",
    "1327": "IDOian",
    "1329": "IDUian",
    "1331": "IRFian",
    "1333": "ITTian",
    "1335": "IBBian",
    "1337": "IFOian",
    "1339": "IFUian",
    "1341": "ICLian",
    "1343": "IRTian",
    "1345": "ISKian",
    "1347": "IGOian",
    "1349": "IGUian",
    "1351": "IFFian",
    "1353": "ISTian",
    "1355": "IPPian",
    "1357": "IHOian",
    "1359": "IHUian",
    "1361": "IJUian",
    "1363": "ISSian",
    "1365": "HOLian",
    "1367": "IGRian",
    "1369": "ITLian",
    "1371": "ALTian",
    "1373": "ILUian",
    "1375": "INTian",
    "1377": "INSian",
    "1379": "ILVian",
    "1381": "IMOian",
    "1383": "IMUian",
    "1385": "ITRian",
    "1387": "LORian",
    "1389": "BADian",
    "1391": "INOian",
    "1393": "INUian",
    "1395": "ILFian",
    "1397": "IRGian",
    "1399": "ISPian",
    "1401": "IPOian",
    "1403": "IPUian",
    "1405": "ITLian",
    "1407": "IRRian",
    "1409": "IMSian",
    "1411": "IROian",
    "1413": "IRUian",
    "1415": "IMPian",
    "1417": "IRKian",
    "1419": "ICKian",
    "1421": "ISOian",
    "1423": "ISUian",
    "1425": "IDRian",
    "1427": "INBian",
    "1429": "ITRian",
    "1431": "ITOian",
    "1433": "ITUian",
    "1435": "IBLian",
    "1437": "IFRian",
    "1439": "IYOian",
    "1441": "JABian",
    "1443": "JACian",
    "1445": "JADian",
    "1447": "JAFian",
    "1449": "JAGian",
    "1451": "FIJian",
    "1453": "AOLian",
    "1455": "JAKian",
    "1457": "JALian",
    "1459": "ESPian",
    "1461": "JUSian",
    "1463": "UGRian",
    "1465": "JAQian",
    "1467": "JARian",
    "1469": "JASian",
    "1471": "JATian",
    "1473": "JAVian",
    "1475": "UFFian",
    "1477": "JEXian",
    "1479": "JEYian",
    "1481": "JEZian",
    "1483": "JEBian",
    "1485": "JECian",
    "1487": "JEDian",
    "1489": "JEFian",
    "1491": "JEGian",
    "1493": "JEHian",
    "1495": "JEJian",
    "1497": "JEKian",
    "1499": "JELian",
    "1501": "MEVian",
    "1503": "JENian",
    "1505": "JEPian",
    "1507": "JEQian",
    "1509": "JIRian",
    "1511": "JISian",
    "1513": "JITian",
    "1515": "JIVian",
    "1517": "JIWian",
    "1519": "JIXian",
    "1521": "JIYian",
    "1523": "THUian",
    "1525": "JIBian",
    "1527": "JICian",
    "1529": "JIDian",
    "1531": "JIFian",
    "1533": "JIGian",
    "1535": "JIHian",
    "1537": "JIJian",
    "1539": "JIKian",
    "1541": "JILian",
    "1543": "JOMian",
    "1545": "JONian",
    "1547": "JOPian",
    "1549": "JOQian",
    "1551": "JORian",
    "1553": "JOSian",
    "1555": "JOTian",
    "1557": "JOVian",
    "1559": "JOWian",
    "1561": "JOXian",
    "1563": "JOYian",
    "1565": "JOZian",
    "1567": "JOBian",
    "1569": "JOCian",
    "1571": "JODian",
    "1573": "JOFian",
    "1575": "JOGian",
    "1577": "JUHian",
    "1579": "JUJian",
    "1581": "JUKian",
    "1583": "JULian",
    "1585": "JUMian",
    "1587": "JUNian",
    "1589": "JUPian",
    "1591": "JUQian",
    "1593": "JURian",
    "1595": "AGRian",
    "1597": "JUTian",
    "1599": "JUVian",
    "1601": "JUWian",
    "1603": "JUXian",
    "1605": "JUYian",
    "1607": "JUZian",
    "1609": "JUBian",
    "1611": "KABian",
    "1613": "KACian",
    "1615": "KADian",
    "1617": "KAFian",
    "1619": "KAGian",
    "1621": "KAHian",
    "1623": "KAJian",
    "1625": "KAKian",
    "1627": "KALian",
    "1629": "KAMian",
    "1631": "KANian",
    "1633": "KAPian",
    "1635": "KAQian",
    "1637": "KARian",
    "1639": "KASian",
    "1641": "KATian",
    "1643": "KAVian",
    "1645": "KEWian",
    "1647": "KEXian",
    "1649": "KEYian",
    "1651": "KEZian",
    "1653": "KEBian",
    "1655": "KECian",
    "1657": "KEDian",
    "1659": "KEFian",
    "1661": "KEGian",
    "1663": "KEHian",
    "1665": "KEJian",
    "1667": "KEKian",
    "1669": "KELian",
    "1671": "KEMian",
    "1673": "KENian",
    "1675": "KEPian",
    "1677": "KEQian",
    "1679": "KIRian",
    "1681": "KISian",
    "1683": "KITian",
    "1685": "KIVian",
    "1687": "KIWian",
    "1689": "KIXian",
    "1691": "KIYian",
    "1693": "KIZian",
    "1695": "KIBian",
    "1697": "KICian",
    "1699": "KIDian",
    "1701": "KIFian",
    "1703": "KIGian",
    "1705": "KIHian",
    "1707": "JANian",
    "1709": "DORian",
    "1711": "KILian",
    "1713": "KOMian",
    "1715": "KONian",
    "1717": "MIXian",
    "1719": "KOQian",
    "1721": "KORian",
    "1723": "KOSian",
    "1725": "KOTian",
    "1727": "KOVian",
    "1729": "KOWian",
    "1731": "KOXian",
    "1733": "KOYian",
    "1735": "KOZian",
    "1737": "KOBian",
    "1739": "KOCian",
    "1741": "PROian",
    "1743": "KOFian",
    "1745": "KOGian",
    "1747": "KUHian",
    "1749": "OVTian",
    "1751": "KUKian",
    "1753": "KULian",
    "1755": "JAMian",
    "1757": "KUNian",
    "1759": "KUPian",
    "1761": "KUQian",
    "1763": "KURian",
    "1765": "KUSian",
    "1767": "KUTian",
    "1769": "KUVian",
    "1771": "KUWian",
    "1773": "KUXian",
    "1775": "KUYian",
    "1777": "KUZian",
    "1779": "KUBian",
    "1781": "LABian",
    "1783": "LACian",
    "1785": "LADian",
    "1787": "LAFian",
    "1789": "LAGian",
    "1791": "LAHian",
    "1793": "LAJian",
    "1795": "LAKian",
    "1797": "LALian",
    "1799": "LAMian",
    "1801": "LANian",
    "1803": "LAPian",
    "1805": "LAQian",
    "1807": "LARian",
    "1809": "LASian",
    "1811": "LATian",
    "1813": "LAVian",
    "1815": "LEWian",
    "1817": "LEXian",
    "1819": "LEYian",
    "1821": "LEZian",
    "1823": "LEBian",
    "1825": "LECian",
    "1827": "LEDian",
    "1829": "LEFian",
    "1831": "LEGian",
    "1833": "LEHian",
    "1835": "LEJian",
    "1837": "LEKian",
    "1839": "LELian",
    "1841": "LEMian",
    "1843": "LENian",
    "1845": "LEPian",
    "1847": "LEQian",
    "1849": "LIRian",
    "1851": "LISian",
    "1853": "LITian",
    "1855": "LIVian",
    "1857": "LIWian",
    "1859": "LIXian",
    "1861": "LIYian",
    "1863": "LIZian",
    "1865": "LIBian",
    "1867": "LICian",
    "1869": "THOian",
    "1871": "LIFian",
    "1873": "LIGian",
    "1875": "LIHian",
    "1877": "LIJian",
    "1879": "LIKian",
    "1881": "LILian",
    "1883": "LOMian",
    "1885": "LONian",
    "1887": "LOPian",
    "1889": "LOQian",
    "1891": "LORian",
    "1893": "LOSian",
    "1895": "LOTian",
    "1897": "LOVian",
    "1899": "LOWian",
    "1901": "LOXian",
    "1903": "LOYian",
    "1905": "LOZian",
    "1907": "LOBian",
    "1909": "SIVian",
    "1911": "LODian",
    "1913": "LOFian",
    "1915": "LOGian",
    "1917": "LUHian",
    "1919": "LUJian",
    "1921": "LUKian",
    "1923": "LULian",
    "1925": "LUMian",
    "1927": "LUNian",
    "1929": "LUPian",
    "1931": "LUQian",
    "1933": "LURian",
    "1935": "LUSian",
    "1937": "LUTian",
    "1939": "LUVian",
    "1941": "LUWian",
    "1943": "LUXian",
    "1945": "LUYian",
    "1947": "LUZian",
    "1949": "LUBian",
    "1951": "MABian",
    "1953": "MACian",
    "1955": "MADian",
    "1957": "MAFian",
    "1959": "MAGian",
    "1961": "MAHian",
    "1963": "MAJian",
    "1965": "MAKian",
    "1967": "MALian",
    "1969": "MAMian",
    "1971": "MANian",
    "1973": "MAPian",
    "1975": "MAQian",
    "1977": "MARian",
    "1979": "MASian",
    "1981": "MATian",
    "1983": "MAVian",
    "1985": "MEWian",
    "1987": "MEXian",
    "1989": "MEYian",
    "1991": "MEZian",
    "1993": "MEBian",
    "1995": "MECian",
    "1997": "MEDian",
    "1999": "MEFian",
    "2001": "MEGian",
    "2003": "MEHian",
    "2005": "MEJian",
    "2007": "MEKian",
    "2009": "EGGian",
    "2011": "MEMian",
    "2013": "MENian",
    "2015": "MEPian",
    "2017": "MEQian",
    "2019": "MIRian",
    "2021": "MISian",
    "2023": "MITian",
    "2025": "MIVian",
    "2027": "MIWian",
    "2029": "ISHian",
    "2031": "MIYian",
    "2033": "MIZian",
    "2035": "MIBian",
    "2037": "MICian",
    "2039": "MIDian",
    "2041": "MIFian",
    "2043": "MIGian",
    "2045": "MIHian",
    "2047": "ANTian",
    "2049": "Eian",
    "2051": "MILian",
    "2053": "POWian",
    "2055": "MONian",
    "2057": "MOPian",
    "2059": "MOQian",
    "2061": "MORian",
    "2063": "MOSian",
    "2065": "MOTian",
    "2067": "MOVian",
    "2069": "MOWian",
    "2071": "MOXian",
    "2073": "MOYian",
    "2075": "MOZian",
    "2077": "MOBian",
    "2079": "MOCian",
    "2081": "MODian",
    "2083": "MOFian",
    "2085": "MOGian",
    "2087": "MUHian",
    "2089": "MUJian",
    "2091": "MUKian",
    "2093": "MULian",
    "2095": "MUMian",
    "2097": "MUNian",
    "2099": "MUPian",
    "2101": "MUQian",
    "2103": "MURian",
    "2105": "RIGian",
    "2107": "MUTian",
    "2109": "MUVian",
    "2111": "MUWian",
    "2113": "MUXian",
    "2115": "MUYian",
    "2117": "JAJian",
    "2119": "MUBian",
    "2121": "NABian",
    "2123": "NACian",
    "2125": "NADian",
    "2127": "NAFian",
    "2129": "NAGian",
    "2131": "NAHian",
    "2133": "NAJian",
    "2135": "NAKian",
    "2137": "NALian",
    "2139": "NAMian",
    "2141": "NANian",
    "2143": "NAPian",
    "2145": "HOTian",
    "2147": "NARian",
    "2149": "NASian",
    "2151": "NATian",
    "2153": "NAVian",
    "2155": "NEWian",
    "2157": "NEXian",
    "2159": "NEYian",
    "2161": "NEZian",
    "2163": "NEBian",
    "2165": "NECian",
    "2167": "NEDian",
    "2169": "NEFian",
    "2171": "NEGian",
    "2173": "NEHian",
    "2175": "NEJian",
    "2177": "BANian",
    "2179": "NELian",
    "2181": "NEMian",
    "2183": "NENian",
    "2185": "ESSian",
    "2187": "NEQian",
    "2189": "NIRian",
    "2191": "NISian",
    "2193": "JEMian",
    "2195": "NIVian",
    "2197": "NIWian",
    "2199": "NIXian",
    "2201": "NIYian",
    "2203": "NIZian",
    "2205": "NIBian",
    "2207": "NICian",
    "2209": "NIDian",
    "2211": "NIFian",
    "2213": "NIGian",
    "2215": "NIHian",
    "2217": "NIJian",
    "2219": "NIKian",
    "2221": "GROian",
    "2223": "NOMian",
    "2225": "KIKian",
    "2227": "NOPian",
    "2229": "NOQian",
    "2231": "NORian",
    "2233": "NOSian",
    "2235": "ATLian",
    "2237": "NOVian",
    "2239": "NOWian",
    "2241": "NOXian",
    "2243": "NOYian",
    "2245": "NOZian",
    "2247": "NOBian",
    "2249": "NOCian",
    "2251": "NODian",
    "2253": "NOFian",
    "2255": "NOGian",
    "2257": "NUHian",
    "2259": "NUJian",
    "2261": "NUKian",
    "2263": "NULian",
    "2265": "NUMian",
    "2267": "NUNian",
    "2269": "NUPian",
    "2271": "NUQian",
    "2273": "NURian",
    "2275": "NUSian",
    "2277": "NUTian",
    "2279": "NUVian",
    "2281": "NUWian",
    "2283": "NUXian",
    "2285": "NUYian",
    "2287": "NUZian",
    "2289": "NUBian",
    "2291": "OSHian",
    "2293": "OTTian",
    "2295": "PHLian",
    "2297": "OBOian",
    "2299": "OBUian",
    "2301": "STRian",
    "2303": "OTHian",
    "2305": "OLLian",
    "2307": "OCOian",
    "2309": "OCUian",
    "2311": "OTRian",
    "2313": "OSRian",
    "2315": "ORKian",
    "2317": "ODOian",
    "2319": "ODUian",
    "2321": "GUMian",
    "2323": "OSTian",
    "2325": "OMPian",
    "2327": "OFOian",
    "2329": "OFUian",
    "2331": "OTWian",
    "2333": "OPLian",
    "2335": "OLFian",
    "2337": "OGOian",
    "2339": "OGUian",
    "2341": "ONBian",
    "2343": "OCLian",
    "2345": "OMSian",
    "2347": "OHOian",
    "2349": "OHUian",
    "2351": "OJUian",
    "2353": "ORTian",
    "2355": "ORFian",
    "2357": "ORRian",
    "2359": "ORMian",
    "2361": "OLOian",
    "2363": "OLUian",
    "2365": "ODRian",
    "2367": "MOMian",
    "2369": "OFFian",
    "2371": "OMOian",
    "2373": "OMUian",
    "2375": "SCOian",
    "2377": "OSKian",
    "2379": "OLTian",
    "2381": "ONOian",
    "2383": "ONUian",
    "2385": "OTRian",
    "2387": "OBRian",
    "2389": "ONKian",
    "2391": "OPOian",
    "2393": "OPUian",
    "2395": "ORGian",
    "2397": "OGGian",
    "2399": "KIJian",
    "2401": "OROian",
    "2403": "ORUian",
    "2405": "FRUian",
    "2407": "OSPian",
    "2409": "OSSian",
    "2411": "OSOian",
    "2413": "OSUian",
    "2415": "ONTian",
    "2417": "OLVian",
    "2419": "OBSian",
    "2421": "OTOian",
    "2423": "OTUian",
    "2425": "OBBian",
    "2427": "ONSian",
    "2429": "OYOian",
    "2431": "PABian",
    "2433": "PACian",
    "2435": "PADian",
    "2437": "PAFian",
    "2439": "PAGian",
    "2441": "PAHian",
    "2443": "PAJian",
    "2445": "PAKian",
    "2447": "PALian",
    "2449": "PAMian",
    "2451": "PANian",
    "2453": "PAPian",
    "2455": "PAQian",
    "2457": "PARian",
    "2459": "PASian",
    "2461": "PATian",
    "2463": "PAVian",
    "2465": "PEWian",
    "2467": "PEXian",
    "2469": "PEYian",
    "2471": "PEZian",
    "2473": "PEBian",
    "2475": "EGRian",
    "2477": "HARian",
    "2479": "PEFian",
    "2481": "PEGian",
    "2483": "PEHian",
    "2485": "PEJian",
    "2487": "PEKian",
    "2489": "PELian",
    "2491": "PEMian",
    "2493": "PENian",
    "2495": "PEPian",
    "2497": "PEQian",
    "2499": "PIRian",
    "2501": "PISian",
    "2503": "PITian",
    "2505": "PIVian",
    "2507": "PIWian",
    "2509": "PIXian",
    "2511": "PIYian",
    "2513": "PIZian",
    "2515": "PIBian",
    "2517": "PICian",
    "2519": "PIDian",
    "2521": "PIFian",
    "2523": "GITian",
    "2525": "PIHian",
    "2527": "PIJian",
    "2529": "PIKian",
    "2531": "PILian",
    "2533": "POMian",
    "2535": "PONian",
    "2537": "POPian",
    "2539": "POQian",
    "2541": "PORian",
    "2543": "POSian",
    "2545": "POTian",
    "2547": "POVian",
    "2549": "UFRian",
    "2551": "POXian",
    "2553": "POYian",
    "2555": "POZian",
    "2557": "POBian",
    "2559": "POCian",
    "2561": "PODian",
    "2563": "POFian",
    "2565": "POGian",
    "2567": "PUHian",
    "2569": "PUJian",
    "2571": "PUKian",
    "2573": "PULian",
    "2575": "PUMian",
    "2577": "PUNian",
    "2579": "PUPian",
    "2581": "PUQian",
    "2583": "PURian",
    "2585": "OTLian",
    "2587": "PUTian",
    "2589": "PUVian",
    "2591": "PUWian",
    "2593": "PUXian",
    "2595": "PUYian",
    "2597": "PUZian",
    "2599": "PUBian",
    "2601": "QABian",
    "2603": "QACian",
    "2605": "QADian",
    "2607": "QAFian",
    "2609": "QAGian",
    "2611": "QAHian",
    "2613": "QAJian",
    "2615": "QAKian",
    "2617": "QELian",
    "2619": "QEMian",
    "2621": "QENian",
    "2623": "QEPian",
    "2625": "ODWian",
    "2627": "QERian",
    "2629": "QESian",
    "2631": "QETian",
    "2633": "QIVian",
    "2635": "QIWian",
    "2637": "QIXian",
    "2639": "QIYian",
    "2641": "QIZian",
    "2643": "QIBian",
    "2645": "QICian",
    "2647": "QIDian",
    "2649": "QOFian",
    "2651": "QOGian",
    "2653": "QOHian",
    "2655": "QOJian",
    "2657": "QOKian",
    "2659": "QOLian",
    "2661": "QOMian",
    "2663": "QONian",
    "2665": "QUPian",
    "2667": "QUQian",
    "2669": "QURian",
    "2671": "QUSian",
    "2673": "QUTian",
    "2675": "QUVian",
    "2677": "QUWian",
    "2679": "QUXian",
    "2681": "RABian",
    "2683": "RACian",
    "2685": "KUMian",
    "2687": "RAFian",
    "2689": "RAGian",
    "2691": "RAHian",
    "2693": "RAJian",
    "2695": "RAKian",
    "2697": "RALian",
    "2699": "SCUian",
    "2701": "RANian",
    "2703": "RAPian",
    "2705": "RAQian",
    "2707": "RARian",
    "2709": "RASian",
    "2711": "RATian",
    "2713": "RAVian",
    "2715": "REWian",
    "2717": "REXian",
    "2719": "REYian",
    "2721": "REZian",
    "2723": "REBian",
    "2725": "RECian",
    "2727": "REDian",
    "2729": "REFian",
    "2731": "REGian",
    "2733": "MELian",
    "2735": "REJian",
    "2737": "REKian",
    "2739": "RELian",
    "2741": "IONian",
    "2743": "RENian",
    "2745": "OPRian",
    "2747": "REQian",
    "2749": "RIRian",
    "2751": "RISian",
    "2753": "RITian",
    "2755": "RIVian",
    "2757": "RIWian",
    "2759": "RIXian",
    "2761": "RIYian",
    "2763": "RIZian",
    "2765": "RIBian",
    "2767": "RICian",
    "2769": "RIDian",
    "2771": "RIFian",
    "2773": "LYDian",
    "2775": "RIHian",
    "2777": "HAPian",
    "2779": "RIKian",
    "2781": "RILian",
    "2783": "ROMian",
    "2785": "RONian",
    "2787": "ROPian",
    "2789": "ROQian",
    "2791": "RORian",
    "2793": "ROSian",
    "2795": "ROTian",
    "2797": "ROVian",
    "2799": "ROWian",
    "2801": "ROXian",
    "2803": "ROYian",
    "2805": "ROZian",
    "2807": "ROBian",
    "2809": "ROCian",
    "2811": "RODian",
    "2813": "ROFian",
    "2815": "ROGian",
    "2817": "RUHian",
    "2819": "RUJian",
    "2821": "RUKian",
    "2823": "RULian",
    "2825": "RUMian",
    "2827": "RUNian",
    "2829": "RUPian",
    "2831": "RUQian",
    "2833": "RURian",
    "2835": "RUSian",
    "2837": "RUTian",
    "2839": "RUVian",
    "2841": "RUWian",
    "2843": "RUXian",
    "2845": "RUYian",
    "2847": "RUZian",
    "2849": "RUBian",
    "2851": "SABian",
    "2853": "SACian",
    "2855": "SADian",
    "2857": "SAFian",
    "2859": "SAGian",
    "2861": "SAHian",
    "2863": "SAJian",
    "2865": "SAKian",
    "2867": "SALian",
    "2869": "SAMian",
    "2871": "SANian",
    "2873": "SAPian",
    "2875": "SAQian",
    "2877": "SARian",
    "2879": "SASian",
    "2881": "SATian",
    "2883": "SAVian",
    "2885": "SEWian",
    "2887": "IGGian",
    "2889": "SEYian",
    "2891": "SEZian",
    "2893": "SEBian",
    "2895": "SECian",
    "2897": "SEDian",
    "2899": "SEFian",
    "2901": "HINian",
    "2903": "SEHian",
    "2905": "SEJian",
    "2907": "SEKian",
    "2909": "SELian",
    "2911": "SEMian",
    "2913": "SENian",
    "2915": "ARGian",
    "2917": "SEQian",
    "2919": "SIRian",
    "2921": "OPSian",
    "2923": "SITian",
    "2925": "VILian",
    "2927": "SIWian",
    "2929": "UTLian",
    "2931": "SIYian",
    "2933": "SIZian",
    "2935": "SIBian",
    "2937": "SICian",
    "2939": "SIDian",
    "2941": "SIFian",
    "2943": "SIGian",
    "2945": "SIHian",
    "2947": "SIJian",
    "2949": "SIKian",
    "2951": "SILian",
    "2953": "SOMian",
    "2955": "SONian",
    "2957": "SOPian",
    "2959": "SOQian",
    "2961": "SORian",
    "2963": "SOSian",
    "2965": "SOTian",
    "2967": "SOVian",
    "2969": "SOWian",
    "2971": "SOXian",
    "2973": "SOYian",
    "2975": "SOZian",
    "2977": "SOBian",
    "2979": "SOCian",
    "2981": "SODian",
    "2983": "SOFian",
    "2985": "SOGian",
    "2987": "SUHian",
    "2989": "SUJian",
    "2991": "SUKian",
    "2993": "SULian",
    "2995": "SUMian",
    "2997": "SUNian",
    "2999": "SUPian",
    "3001": "SUQian",
    "3003": "SURian",
    "3005": "ASKian",
    "3007": "SUTian",
    "3009": "SUVian",
    "3011": "SUWian",
    "3013": "SUXian",
    "3015": "SUYian",
    "3017": "SUZian",
    "3019": "SUBian",
    "3021": "TABian",
    "3023": "TACian",
    "3025": "TADian",
    "3027": "TAFian",
    "3029": "TAGian",
    "3031": "TAHian",
    "3033": "TAJian",
    "3035": "TAKian",
    "3037": "TALian",
    "3039": "TAMian",
    "3041": "TANian",
    "3043": "TAPian",
    "3045": "TAQian",
    "3047": "TARian",
    "3049": "TASian",
    "3051": "TATian",
    "3053": "TAVian",
    "3055": "TEWian",
    "3057": "TEXian",
    "3059": "TEYian",
    "3061": "TEZian",
    "3063": "TEBian",
    "3065": "TECian",
    "3067": "TEDian",
    "3069": "TEFian",
    "3071": "RAYian",
    "3073": "TEHian",
    "3075": "ATRian",
    "3077": "TEKian",
    "3079": "TELian",
    "3081": "TEMian",
    "3083": "REHian",
    "3085": "TEPian",
    "3087": "TEQian",
    "3089": "TIRian",
    "3091": "TISian",
    "3093": "BUQian",
    "3095": "TIVian",
    "3097": "TIWian",
    "3099": "TIXian",
    "3101": "TIYian",
    "3103": "ADRian",
    "3105": "TIBian",
    "3107": "TICian",
    "3109": "TIDian",
    "3111": "TIFian",
    "3113": "TIGian",
    "3115": "TIHian",
    "3117": "TIJian",
    "3119": "TIKian",
    "3121": "TILian",
    "3123": "TOMian",
    "3125": "TONian",
    "3127": "TOPian",
    "3129": "TOQian",
    "3131": "TORian",
    "3133": "TOSian",
    "3135": "TOTian",
    "3137": "TOVian",
    "3139": "TOWian",
    "3141": "TOXian",
    "3143": "TOYian",
    "3145": "TOZian",
    "3147": "TOBian",
    "3149": "TOCian",
    "3151": "TODian",
    "3153": "TOFian",
    "3155": "TOGian",
    "3157": "GRUian",
    "3159": "TUJian",
    "3161": "TUKian",
    "3163": "TULian",
    "3165": "TUMian",
    "3167": "TUNian",
    "3169": "TUPian",
    "3171": "TUQian",
    "3173": "TURian",
    "3175": "EFRian",
    "3177": "TUTian",
    "3179": "TUVian",
    "3181": "TUWian",
    "3183": "TUXian",
    "3185": "BROian",
    "3187": "TUZian",
    "3189": "TUBian",
    "3191": "URMian",
    "3193": "USRian",
    "3195": "SCRian",
    "3197": "UBOian",
    "3199": "UBUian",
    "3201": "URTian",
    "3203": "ETRian",
    "3205": "UTWian",
    "3207": "UCOian",
    "3209": "UCUian",
    "3211": "UTHian",
    "3213": "URKian",
    "3215": "UCLian",
    "3217": "UDOian",
    "3219": "UDUian",
    "3221": "UMSian",
    "3223": "UNSian",
    "3225": "ULFian",
    "3227": "UFOian",
    "3229": "UFUian",
    "3231": "USHian",
    "3233": "UNBian",
    "3235": "UNTian",
    "3237": "UGOian",
    "3239": "UGUian",
    "3241": "UPSian",
    "3243": "UTRian",
    "3245": "DEFian",
    "3247": "UHOian",
    "3249": "UHUian",
    "3251": "UJUian",
    "3253": "UCHian",
    "3255": "UTRian",
    "3257": "UPLian",
    "3259": "CHOian",
    "3261": "ULOian",
    "3263": "ULUian",
    "3265": "URRian",
    "3267": "URFian",
    "3269": "UCKian",
    "3271": "UMOian",
    "3273": "UMUian",
    "3275": "UBSian",
    "3277": "USPian",
    "3279": "USKian",
    "3281": "UNOian",
    "3283": "UNUian",
    "3285": "UNKian",
    "3287": "UPHian",
    "3289": "UBLian",
    "3291": "UPOian",
    "3293": "UPUian",
    "3295": "URAian",
    "3297": "ULLian",
    "3299": "UBRian",
    "3301": "UROian",
    "3303": "URUian",
    "3305": "UMPian",
    "3307": "ULKian",
    "3309": "UPPian",
    "3311": "USOian",
    "3313": "USUian",
    "3315": "UBBian",
    "3317": "URGian",
    "3319": "UTTian",
    "3321": "UTOian",
    "3323": "UTUian",
    "3325": "USSian",
    "3327": "KUJian",
    "3329": "UYOian",
    "3331": "VABian",
    "3333": "VACian",
    "3335": "VADian",
    "3337": "VAFian",
    "3339": "SMUian",
    "3341": "VAHian",
    "3343": "VAJian",
    "3345": "VAKian",
    "3347": "DRUian",
    "3349": "VAMian",
    "3351": "VANian",
    "3353": "VAPian",
    "3355": "VAQian",
    "3357": "VARian",
    "3359": "VASian",
    "3361": "VATian",
    "3363": "VAVian",
    "3365": "VEWian",
    "3367": "VEXian",
    "3369": "VEYian",
    "3371": "VEZian",
    "3373": "VEBian",
    "3375": "VECian",
    "3377": "VEDian",
    "3379": "VEFian",
    "3381": "VEGian",
    "3383": "VEHian",
    "3385": "VEJian",
    "3387": "VEKian",
    "3389": "VELian",
    "3391": "VEMian",
    "3393": "VENian",
    "3395": "VEPian",
    "3397": "VEQian",
    "3399": "VIRian",
    "3401": "VISian",
    "3403": "VITian",
    "3405": "VIVian",
    "3407": "VIWian",
    "3409": "VIXian",
    "3411": "VIYian",
    "3413": "VIZian",
    "3415": "VIBian",
    "3417": "VICian",
    "3419": "VIDian",
    "3421": "VIFian",
    "3423": "VIGian",
    "3425": "VIHian",
    "3427": "VIJian",
    "3429": "VIKian",
    "3431": "UGGian",
    "3433": "VOMian",
    "3435": "VONian",
    "3437": "VOPian",
    "3439": "VOQian",
    "3441": "VORian",
    "3443": "VOSian",
    "3445": "VOTian",
    "3447": "VOVian",
    "3449": "VOWian",
    "3451": "VOXian",
    "3453": "VOYian",
    "3455": "VOZian",
    "3457": "VOBian",
    "3459": "VOCian",
    "3461": "VODian",
    "3463": "VOFian",
    "3465": "VOGian",
    "3467": "VUHian",
    "3469": "VUJian",
    "3471": "VUKian",
    "3473": "VULian",
    "3475": "VUMian",
    "3477": "VUNian",
    "3479": "VUPian",
    "3481": "VUQian",
    "3483": "VURian",
    "3485": "VUSian",
    "3487": "VUTian",
    "3489": "VUVian",
    "3491": "VUWian",
    "3493": "VUXian",
    "3495": "VUYian",
    "3497": "VUZian",
    "3499": "VUBian",
    "3501": "WABian",
    "3503": "WACian",
    "3505": "WADian",
    "3507": "WAFian",
    "3509": "WAGian",
    "3511": "WAHian",
    "3513": "WAJian",
    "3515": "WAKian",
    "3517": "WALian",
    "3519": "WAMian",
    "3521": "WANian",
    "3523": "WAPian",
    "3525": "WAQian",
    "3527": "SHOian",
    "3529": "WASian",
    "3531": "WATian",
    "3533": "WAVian",
    "3535": "WEWian",
    "3537": "WEXian",
    "3539": "WEYian",
    "3541": "WEZian",
    "3543": "WEBian",
    "3545": "WECian",
    "3547": "WEDian",
    "3549": "WEFian",
    "3551": "WEGian",
    "3553": "WEHian",
    "3555": "WEJian",
    "3557": "WEKian",
    "3559": "WELian",
    "3561": "WEMian",
    "3563": "WENian",
    "3565": "WEPian",
    "3567": "WEQian",
    "3569": "WIRian",
    "3571": "WISian",
    "3573": "WITian",
    "3575": "WIVian",
    "3577": "WIWian",
    "3579": "WIXian",
    "3581": "WIYian",
    "3583": "RAMian",
    "3585": "WIBian",
    "3587": "WICian",
    "3589": "WIDian",
    "3591": "WIFian",
    "3593": "WIGian",
    "3595": "WIHian",
    "3597": "WIJian",
    "3599": "WIKian",
    "3601": "WILian",
    "3603": "WOMian",
    "3605": "OLKian",
    "3607": "WOPian",
    "3609": "WOQian",
    "3611": "WORian",
    "3613": "WOSian",
    "3615": "WOTian",
    "3617": "WOVian",
    "3619": "WOWian",
    "3621": "WOXian",
    "3623": "WOYian",
    "3625": "WOZian",
    "3627": "WOBian",
    "3629": "WOCian",
    "3631": "WODian",
    "3633": "WOFian",
    "3635": "WOGian",
    "3637": "WUHian",
    "3639": "WUJian",
    "3641": "WUKian",
    "3643": "WULian",
    "3645": "WUMian",
    "3647": "SHUian",
    "3649": "WUPian",
    "3651": "WUQian",
    "3653": "WURian",
    "3655": "WUSian",
    "3657": "WUTian",
    "3659": "WUVian",
    "3661": "WUWian",
    "3663": "WUXian",
    "3665": "WUYian",
    "3667": "WUZian",
    "3669": "WUBian",
    "3671": "XABian",
    "3673": "XACian",
    "3675": "XADian",
    "3677": "XAFian",
    "3679": "XAGian",
    "3681": "XAHian",
    "3683": "XAJian",
    "3685": "XAKian",
    "3687": "XELian",
    "3689": "XEMian",
    "3691": "XENian",
    "3693": "XEPian",
    "3695": "XEQian",
    "3697": "XERian",
    "3699": "XESian",
    "3701": "XETian",
    "3703": "XIVian",
    "3705": "XIWian",
    "3707": "XIXian",
    "3709": "XIYian",
    "3711": "XIZian",
    "3713": "XIBian",
    "3715": "XICian",
    "3717": "XIDian",
    "3719": "XOFian",
    "3721": "XOGian",
    "3723": "XOHian",
    "3725": "XOJian",
    "3727": "XOKian",
    "3729": "XOLian",
    "3731": "XOMian",
    "3733": "XONian",
    "3735": "XUPian",
    "3737": "XUQian",
    "3739": "XURian",
    "3741": "XUSian",
    "3743": "XUTian",
    "3745": "XUVian",
    "3747": "XUWian",
    "3749": "XUXian",
    "3751": "YABian",
    "3753": "YACian",
    "3755": "YADian",
    "3757": "YAFian",
    "3759": "YAGian",
    "3761": "YAHian",
    "3763": "YAJian",
    "3765": "YAKian",
    "3767": "YALian",
    "3769": "YAMian",
    "3771": "YANian",
    "3773": "YAPian",
    "3775": "YAQian",
    "3777": "YARian",
    "3779": "YASian",
    "3781": "YATian",
    "3783": "YAVian",
    "3785": "YEWian",
    "3787": "YEXian",
    "3789": "YEYian",
    "3791": "YEZian",
    "3793": "YEBian",
    "3795": "YECian",
    "3797": "YEDian",
    "3799": "YEFian",
    "3801": "YEGian",
    "3803": "YEHian",
    "3805": "YEJian",
    "3807": "YEKian",
    "3809": "YELian",
    "3811": "YEMian",
    "3813": "YENian",
    "3815": "YEPian",
    "3817": "YEQian",
    "3819": "YIRian",
    "3821": "YISian",
    "3823": "YITian",
    "3825": "YIVian",
    "3827": "YIWian",
    "3829": "YIXian",
    "3831": "YIYian",
    "3833": "YIZian",
    "3835": "YIBian",
    "3837": "YICian",
    "3839": "COWian",
    "3841": "YIFian",
    "3843": "YIGian",
    "3845": "YIHian",
    "3847": "YIJian",
    "3849": "YIKian",
    "3851": "YILian",
    "3853": "YOMian",
    "3855": "YONian",
    "3857": "YOPian",
    "3859": "YOQian",
    "3861": "YORian",
    "3863": "YOSian",
    "3865": "YOTian",
    "3867": "YOVian",
    "3869": "YOWian",
    "3871": "YOXian",
    "3873": "YOYian",
    "3875": "YOZian",
    "3877": "YOBian",
    "3879": "YOCian",
    "3881": "YODian",
    "3883": "YOFian",
    "3885": "YOGian",
    "3887": "YUHian",
    "3889": "YUJian",
    "3891": "YUKian",
    "3893": "YULian",
    "3895": "YUMian",
    "3897": "YUNian",
    "3899": "YUPian",
    "3901": "YUQian",
    "3903": "YURian",
    "3905": "YUSian",
    "3907": "YUTian",
    "3909": "YUVian",
    "3911": "YUWian",
    "3913": "YUXian",
    "3915": "YUYian",
    "3917": "YUZian",
    "3919": "YUBian",
    "3921": "ZABian",
    "3923": "ZACian",
    "3925": "ZADian",
    "3927": "ZAFian",
    "3929": "ZAGian",
    "3931": "ZAHian",
    "3933": "ZAJian",
    "3935": "ZAKian",
    "3937": "ZALian",
    "3939": "ZAMian",
    "3941": "ZANian",
    "3943": "ZAPian",
    "3945": "ZAQian",
    "3947": "GIRian",
    "3949": "ZASian",
    "3951": "ZATian",
    "3953": "ZAVian",
    "3955": "ZEWian",
    "3957": "ZEXian",
    "3959": "ZEYian",
    "3961": "ZEZian",
    "3963": "ZEBian",
    "3965": "ZECian",
    "3967": "CATian",
    "3969": "ZEFian",
    "3971": "ZEGian",
    "3973": "ZEHian",
    "3975": "ZEJian",
    "3977": "ZEKian",
    "3979": "ZELian",
    "3981": "ZEMian",
    "3983": "ZENian",
    "3985": "ZEPian",
    "3987": "ZEQian",
    "3989": "KODian",
    "3991": "ZISian",
    "3993": "ZITian",
    "3995": "ZIVian",
    "3997": "ZIWian",
    "3999": "ZIXian",
    "4001": "ZIYian",
    "4003": "ZIZian",
    "4005": "ZIBian",
    "4007": "ZICian",
    "4009": "ZIDian",
    "4011": "ZIFian",
    "4013": "ZIGian",
    "4015": "ZIHian",
    "4017": "ZIJian",
    "4019": "ZIKian",
    "4021": "ZILian",
    "4023": "ZOMian",
    "4025": "ZONian",
    "4027": "ZOPian",
    "4029": "ZOQian",
    "4031": "BATian",
    "4033": "ZOSian",
    "4035": "ZOTian",
    "4037": "ZOVian",
    "4039": "ZOWian",
    "4041": "ZOXian",
    "4043": "ZOYian",
    "4045": "ZOZian",
    "4047": "ZOBian",
    "4049": "ZOCian",
    "4051": "ZODian",
    "4053": "ZOFian",
    "4055": "ZOGian",
    "4057": "ZUHian",
    "4059": "ZUJian",
    "4061": "ZUKian",
    "4063": "DOGian",
    "4065": "APLian",
    "4067": "ZUNian",
    "4069": "ZUPian",
    "4071": "ZUQian",
    "4073": "ZURian",
    "4075": "ZUSian",
    "4077": "ZUTian",
    "4079": "PIGian",
    "4081": "ZUWian",
    "4083": "ZUXian",
    "4085": "ZUYian",
    "4087": "YAKian",
    "4089": "ZUBian",
    "4091": "EELian",
    "4093": "FLYian",
    "4095": "CROMian"
}